sphinxcontrib_indesignbuilder-0.1.1-nspkg.pth
sphinxcontrib/directives.py
sphinxcontrib/indesignbuilder.py
sphinxcontrib/webdbbuilder.py
sphinxcontrib/webdbwriter.py
sphinxcontrib/writer.py
sphinxcontrib/indesignbuilder/__init__.py
sphinxcontrib/indesignbuilder/directives.py
sphinxcontrib/indesignbuilder/indesignbuilder.py
sphinxcontrib/indesignbuilder/transforms.py
sphinxcontrib/indesignbuilder/webdbwriter.py
sphinxcontrib/indesignbuilder/writer.py
sphinxcontrib_indesignbuilder-0.1.1.dist-info/METADATA
sphinxcontrib_indesignbuilder-0.1.1.dist-info/WHEEL
sphinxcontrib_indesignbuilder-0.1.1.dist-info/namespace_packages.txt
sphinxcontrib_indesignbuilder-0.1.1.dist-info/top_level.txt
sphinxcontrib_indesignbuilder-0.1.1.dist-info/RECORD
