Metadata-Version: 2.1
Name: sphinxcontrib-indesignbuilder
Version: 0.1.1
Summary: Sphinx indesign builder
Home-page: http://github.com/shirou/sphinxcontrib-indesignbuilder
Author: WAKAYAMA Shirou
Author-email: shirou.faw@gmail.com
License: BSD
Download-URL: http://pypi.python.org/pypi/sphinxcontrib-indesignbuilder
Platform: any
Classifier: Development Status :: 4 - Beta
Classifier: Environment :: Console
Classifier: Intended Audience :: Developers
Classifier: License :: OSI Approved :: BSD License
Classifier: Operating System :: OS Independent
Classifier: Programming Language :: Python
Classifier: Topic :: Documentation
Classifier: Topic :: Utilities
Requires-Dist: Sphinx (>=1.6)
Requires-Dist: setuptools
